gam_web_apis/ExchangeSettingsService.py
gam_web_apis/PolicyService.py
gam_web_apis/PricingRuleService.py
gam_web_apis/ProtectionService.py
gam_web_apis/Statement.py
gam_web_apis/TargetingService.py
gam_web_apis/__init__.py
gam_web_apis/__lib_AccountPolicySummary__.py
gam_web_apis/__lib_EntityPolicyStats__.py
gam_web_apis/__lib_ExchangeSettings__.py
gam_web_apis/__lib_PolicySession__.py
gam_web_apis/__lib_PricingRule__.py
gam_web_apis/__lib_ServiceManager__.py
gam_web_apis/__lib_Targeting__.py
gam_web_apis/__lib__.py
gam_web_apis/__lib_abstractions__.py
gam_web_apis/__lib_internal__.py
gam_web_apis/__lib_math__.py
gam_web_apis/__lib_session__.py
gam_web_apis/__lib_tools__.py
gam_web_apis-0.0.3.dist-info/LICENSE.txt
gam_web_apis-0.0.3.dist-info/METADATA
gam_web_apis-0.0.3.dist-info/WHEEL
gam_web_apis-0.0.3.dist-info/top_level.txt
gam_web_apis-0.0.3.dist-info/RECORD
