Metadata-Version: 2.1
Name: gam-web-apis
Version: 0.0.3
Summary: A small example package
Home-page: https://github.com/BerendKemper/gam-web-apis
Author: Kemper Software Solutions
Author-email: Berend Kemper <berend_kemper@hotmail.com>
Project-URL: Homepage, https://github.com/BerendKemper/gam-web-apis
Project-URL: Bug Tracker, https://github.com/BerendKemper/gam-web-apis/issues
Keywords: sample,setuptools,development,Google Ad Manager,PricingRuleService
Classifier: Programming Language :: Python :: 3
Classifier: License :: OSI Approved :: MIT License
Classifier: Operating System :: OS Independent
Requires-Python: >=3.7, <4
License-File: LICENSE.txt
Requires-Dist: requests
